llmrf/__init__.py
llmrf/rf.py
llmrf-0.1.4.dist-info/METADATA
llmrf-0.1.4.dist-info/WHEEL
llmrf-0.1.4.dist-info/top_level.txt
llmrf-0.1.4.dist-info/RECORD
