Metadata-Version: 2.2
Name: llmrf
Version: 0.1.4
Summary: 轻量级的 LLM 响应格式化工具，支持标准响应和流式响应
Home-page: https://github.com/cchking/llmrf
Author: 满天翔
Author-email: 2722843861@qq.com
Classifier: Programming Language :: Python :: 3
Classifier: License :: OSI Approved :: MIT License
Classifier: Operating System :: OS Independent
Requires-Python: >=3.6
Dynamic: author
Dynamic: author-email
Dynamic: classifier
Dynamic: description
Dynamic: description-content-type
Dynamic: home-page
Dynamic: requires-python
Dynamic: summary
